{
  "author": "NetScout-Go",
  "description": "Captures and analyzes network traffic using tcpdump",
  "icon": "traffic",
  "id": "packet_capture",
  "license": "MIT",
  "name": "Network Packet Capture",
  "parameters": [
    {
      "default": "eth0",
      "description": "The network interface to capture packets from",
      "id": "interface",
      "name": "Network Interface",
      "required": true,
      "type": "string"
    },
    {
      "default": "",
      "description": "BPF filter expression to filter packets (e.g., 'port 80', 'host 192.168.1.1')",
      "id": "capture_filter",
      "name": "Capture Filter",
      "required": false,
      "type": "string"
    },
    {
      "default": 100,
      "description": "Number of packets to capture (0 for unlimited)",
      "id": "packet_count",
      "max": 10000,
      "min": 0,
      "name": "Packet Count",
      "required": false,
      "step": 10,
      "type": "number"
    },
    {
      "default": 10,
      "description": "Time in seconds to capture packets (0 for unlimited)",
      "id": "capture_timeout",
      "max": 300,
      "min": 0,
      "name": "Capture Timeout",
      "required": false,
      "step": 5,
      "type": "number"
    },
    {
      "default": true,
      "description": "Include packet headers in output",
      "id": "include_headers",
      "name": "Include Headers",
      "required": false,
      "type": "boolean"
    }
  ],
  "repository": "https://github.com/NetScout-Go/Plugin_packet_capture",
  "version": "1.0.0"
}